odoo/addons/sale_margin_update/README.rst
odoo/addons/sale_margin_update/__init__.py
odoo/addons/sale_margin_update/__manifest__.py
odoo/addons/sale_margin_update/i18n/es.po
odoo/addons/sale_margin_update/i18n/sale_margin_update.pot
odoo/addons/sale_margin_update/models/__init__.py
odoo/addons/sale_margin_update/models/sale_order.py
odoo/addons/sale_margin_update/models/sale_order_line.py
odoo/addons/sale_margin_update/security/ir.model.access.csv
odoo/addons/sale_margin_update/static/description/icon.png
odoo/addons/sale_margin_update/static/description/index.html
odoo/addons/sale_margin_update/tests/__init__.py
odoo/addons/sale_margin_update/tests/test_recalculate_price_margin.py
odoo/addons/sale_margin_update/views/sale_order_views.xml
odoo/addons/sale_margin_update/wizard/__init__.py
odoo/addons/sale_margin_update/wizard/recalculate_price_margin.py
odoo/addons/sale_margin_update/wizard/recalculate_price_margin.xml
odoo_addon_sale_margin_update-16.0.1.0.0.1.dist-info/METADATA
odoo_addon_sale_margin_update-16.0.1.0.0.1.dist-info/WHEEL
odoo_addon_sale_margin_update-16.0.1.0.0.1.dist-info/top_level.txt
odoo_addon_sale_margin_update-16.0.1.0.0.1.dist-info/RECORD
