Metadata-Version: 2.1
Name: odoo-addon-sale_margin_update
Version: 16.0.1.0.0.1
Summary: Recalculate expected unit price from margin.
Home-page: https://github.com/OCA/sale-workflow
Author: Oscar Soto, Sidoo Soluciones S.L., Odoo Community Association (OCA)
Author-email: support@odoo-community.org
License: LGPL-3
Classifier: Programming Language :: Python
Classifier: Framework :: Odoo
Classifier: Framework :: Odoo :: 16.0
Classifier: License :: OSI Approved :: GNU Lesser General Public License v3 (LGPLv3)
Requires-Python: >=3.10
Requires-Dist: odoo<16.1dev,>=16.0a
